Ytdl_1080p/__init__.py
Ytdl_1080p/main.py
Ytdl_1080p/test.py
ytdl_hd-0.1.dist-info/LICENSE
ytdl_hd-0.1.dist-info/METADATA
ytdl_hd-0.1.dist-info/WHEEL
ytdl_hd-0.1.dist-info/entry_points.txt
ytdl_hd-0.1.dist-info/top_level.txt
ytdl_hd-0.1.dist-info/RECORD
