Metadata-Version: 2.1
Name: ytdl_hd
Version: 0.1
Summary: ytdl is a command line tool to search and download videos in 1080p from yt using the command line.
Author: Tanish
Author-email: sharmatanish0907@gmail.com
Keywords: python,ytdl_1080p,ytdl-1080p,ytdl 1080p,1080p,ytdl1080p,youtube,youtube downloader,ytdl,Ytdl,1080p yt downloader,downloader,pytube
License-File: LICENSE
Requires-Dist: yt-dlp
Requires-Dist: ffmpeg-python
Requires-Dist: click
Requires-Dist: rich
Requires-Dist: pandas
